<?xml version="1.0" encoding="utf-8"?>
<clothing-items>
 <clothing>
  <id>
   318848357
  </id>
  <name>
   Vans Blouse L-5240
  </name>
  <category>
   Blouse
  </category>
  <size>
   S
  </size>
  <color>
   Красный
  </color>
  <material>
   Нейлон
  </material>
  <price>
   790066
  </price>
  <rating>
   4.67
  </rating>
  <reviews>
   126363
  </reviews>
  <new>
   -
  </new>
  <exclusive>
   no
  </exclusive>
  <sporty>
   yes
  </sporty>
 </clothing>
 <clothing>
  <id>
   301656533
  </id>
  <name>
   Addidas Socks H-4623
  </name>
  <category>
   Socks
  </category>
  <size>
   M
  </size>
  <color>
   Синий
  </color>
  <material>
   Кожа
  </material>
  <price>
   577184
  </price>
  <rating>
   3.49
  </rating>
  <reviews>
   713161
  </reviews>
  <sporty>
   yes
  </sporty>
 </clothing>
 <clothing>
  <id>
   978810527
  </id>
  <name>
   Under Armour Socks I-4190
  </name>
  <category>
   Socks
  </category>
  <size>
   XXL
  </size>
  <color>
   Фиолетовый
  </color>
  <material>
   Шерсть
  </material>
  <price>
   274009
  </price>
  <rating>
   1.25
  </rating>
  <reviews>
   142299
  </reviews>
  <new>
   -
  </new>
  <sporty>
   no
  </sporty>
 </clothing>
 <clothing>
  <id>
   129977374
  </id>
  <name>
   Asics Hat B-2439
  </name>
  <category>
   Hat
  </category>
  <size>
   S
  </size>
  <color>
   Фиолетовый
  </color>
  <material>
   Шелк
  </material>
  <price>
   983042
  </price>
  <rating>
   4.27
  </rating>
  <reviews>
   954131
  </reviews>
  <new>
   -
  </new>
  <exclusive>
   no
  </exclusive>
  <sporty>
   no
  </sporty>
 </clothing>
 <clothing>
  <id>
   482134775
  </id>
  <name>
   New Balance Skirt B-6752
  </name>
  <category>
   Skirt
  </category>
  <size>
   S
  </size>
  <color>
   Желтый
  </color>
  <material>
   Шерсть
  </material>
  <price>
   357663
  </price>
  <rating>
   1.95
  </rating>
  <reviews>
   520864
  </reviews>
  <new>
   +
  </new>
  <sporty>
   no
  </sporty>
 </clothing>
 <clothing>
  <id>
   178157766
  </id>
  <name>
   Reebok Belts C-2291
  </name>
  <category>
   Belts
  </category>
  <size>
   XL
  </size>
  <color>
   Красный
  </color>
  <material>
   Шерсть
  </material>
  <price>
   825784
  </price>
  <rating>
   2.36
  </rating>
  <reviews>
   697934
  </reviews>
  <sporty>
   yes
  </sporty>
 </clothing>
 <clothing>
  <id>
   105129789
  </id>
  <name>
   Brooks Pants C-8318
  </name>
  <category>
   Pants
  </category>
  <size>
   L
  </size>
  <color>
   Оранжевый
  </color>
  <material>
   Нейлон
  </material>
  <price>
   132673
  </price>
  <rating>
   1.53
  </rating>
  <reviews>
   455961
  </reviews>
  <sporty>
   no
  </sporty>
 </clothing>
 <clothing>
  <id>
   369864424
  </id>
  <name>
   Ellesse Gloves B-4450
  </name>
  <category>
   Gloves
  </category>
  <size>
   XL
  </size>
  <color>
   Зеленый
  </color>
  <material>
   Вискоза
  </material>
  <price>
   953496
  </price>
  <rating>
   2.08
  </rating>
  <reviews>
   287063
  </reviews>
  <exclusive>
   no
  </exclusive>
 </clothing>
 <clothing>
  <id>
   394915118
  </id>
  <name>
   Adidas Dress H-7136
  </name>
  <category>
   Dress
  </category>
  <size>
   XL
  </size>
  <color>
   Красный
  </color>
  <material>
   Кожа
  </material>
  <price>
   433608
  </price>
  <rating>
   3.0
  </rating>
  <reviews>
   769060
  </reviews>
  <new>
   -
  </new>
  <exclusive>
   yes
  </exclusive>
  <sporty>
   no
  </sporty>
 </clothing>
 <clothing>
  <id>
   735839416
  </id>
  <name>
   Lacoste Sweater E-4908
  </name>
  <category>
   Sweater
  </category>
  <size>
   M
  </size>
  <color>
   Фиолетовый
  </color>
  <material>
   Кожа
  </material>
  <price>
   126323
  </price>
  <rating>
   1.24
  </rating>
  <reviews>
   510940
  </reviews>
  <new>
   -
  </new>
  <sporty>
   no
  </sporty>
 </clothing>
 <clothing>
  <id>
   165980200
  </id>
  <name>
   Brooks Jeans Q-1156
  </name>
  <category>
   Jeans
  </category>
  <size>
   M
  </size>
  <color>
   Оранжевый
  </color>
  <material>
   Лен
  </material>
  <price>
   855605
  </price>
  <rating>
   2.19
  </rating>
  <reviews>
   712575
  </reviews>
  <new>
   -
  </new>
  <exclusive>
   yes
  </exclusive>
  <sporty>
   yes
  </sporty>
 </clothing>
 <clothing>
  <id>
   735037225
  </id>
  <name>
   Vans Hat C-3792
  </name>
  <category>
   Hat
  </category>
  <size>
   M
  </size>
  <color>
   Голубой
  </color>
  <material>
   Хлопок
  </material>
  <price>
   302489
  </price>
  <rating>
   3.03
  </rating>
  <reviews>
   437685
  </reviews>
 </clothing>
 <clothing>
  <id>
   429645571
  </id>
  <name>
   Nike Hat V-8261
  </name>
  <category>
   Hat
  </category>
  <size>
   S
  </size>
  <color>
   Зеленый
  </color>
  <material>
   Хлопок
  </material>
  <price>
   714558
  </price>
  <rating>
   4.42
  </rating>
  <reviews>
   448330
  </reviews>
  <exclusive>
   yes
  </exclusive>
 </clothing>
 <clothing>
  <id>
   643854162
  </id>
  <name>
   Lacoste Belts F-2530
  </name>
  <category>
   Belts
  </category>
  <size>
   XL
  </size>
  <color>
   Желтый
  </color>
  <material>
   Полиэстер
  </material>
  <price>
   372622
  </price>
  <rating>
   4.5
  </rating>
  <reviews>
   800786
  </reviews>
 </clothing>
 <clothing>
  <id>
   639086980
  </id>
  <name>
   Ellesse Belts G-3702
  </name>
  <category>
   Belts
  </category>
  <size>
   XL
  </size>
  <color>
   Голубой
  </color>
  <material>
   Кожа
  </material>
  <price>
   846837
  </price>
  <rating>
   2.35
  </rating>
  <reviews>
   581534
  </reviews>
  <sporty>
   yes
  </sporty>
 </clothing>
 <clothing>
  <id>
   841269878
  </id>
  <name>
   New Balance T-shirt F-4825
  </name>
  <category>
   T-shirt
  </category>
  <size>
   L
  </size>
  <color>
   Фиолетовый
  </color>
  <material>
   Шелк
  </material>
  <price>
   230897
  </price>
  <rating>
   4.1
  </rating>
  <reviews>
   864199
  </reviews>
  <new>
   -
  </new>
  <sporty>
   no
  </sporty>
 </clothing>
 <clothing>
  <id>
   924962455
  </id>
  <name>
   Adidas Handbags V-4350
  </name>
  <category>
   Handbags
  </category>
  <size>
   M
  </size>
  <color>
   Синий
  </color>
  <material>
   Кожа
  </material>
  <price>
   355384
  </price>
  <rating>
   3.33
  </rating>
  <reviews>
   817637
  </reviews>
  <new>
   -
  </new>
  <exclusive>
   yes
  </exclusive>
 </clothing>
 <clothing>
  <id>
   529522018
  </id>
  <name>
   Vans Jacket Q-6522
  </name>
  <category>
   Jacket
  </category>
  <size>
   M
  </size>
  <color>
   Синий
  </color>
  <material>
   Полиэстер
  </material>
  <price>
   319541
  </price>
  <rating>
   1.5
  </rating>
  <reviews>
   690605
  </reviews>
 </clothing>
 <clothing>
  <id>
   855696959
  </id>
  <name>
   Addidas Pants M-5221
  </name>
  <category>
   Pants
  </category>
  <size>
   XXL
  </size>
  <color>
   Голубой
  </color>
  <material>
   Шерсть
  </material>
  <price>
   876373
  </price>
  <rating>
   1.55
  </rating>
  <reviews>
   579023
  </reviews>
  <new>
   +
  </new>
  <exclusive>
   no
  </exclusive>
  <sporty>
   yes
  </sporty>
 </clothing>
 <clothing>
  <id>
   859676974
  </id>
  <name>
   Nike Shirt Z-8284
  </name>
  <category>
   Shirt
  </category>
  <size>
   XL
  </size>
  <color>
   Желтый
  </color>
  <material>
   Хлопок
  </material>
  <price>
   650978
  </price>
  <rating>
   3.24
  </rating>
  <reviews>
   964188
  </reviews>
  <exclusive>
   no
  </exclusive>
 </clothing>
 <clothing>
  <id>
   629753471
  </id>
  <name>
   Under Armour Hat B-9179
  </name>
  <category>
   Hat
  </category>
  <size>
   XXL
  </size>
  <color>
   Синий
  </color>
  <material>
   Хлопок
  </material>
  <price>
   281444
  </price>
  <rating>
   1.44
  </rating>
  <reviews>
   139886
  </reviews>
  <new>
   -
  </new>
  <exclusive>
   yes
  </exclusive>
  <sporty>
   no
  </sporty>
 </clothing>
 <clothing>
  <id>
   601044761
  </id>
  <name>
   New Balance Shoes H-7900
  </name>
  <category>
   Shoes
  </category>
  <size>
   S
  </size>
  <color>
   Желтый
  </color>
  <material>
   Хлопок
  </material>
  <price>
   747374
  </price>
  <rating>
   3.68
  </rating>
  <reviews>
   818251
  </reviews>
  <exclusive>
   yes
  </exclusive>
  <sporty>
   yes
  </sporty>
 </clothing>
 <clothing>
  <id>
   398388168
  </id>
  <name>
   Under Armour Skirt B-7935
  </name>
  <category>
   Skirt
  </category>
  <size>
   S
  </size>
  <color>
   Желтый
  </color>
  <material>
   Шелк
  </material>
  <price>
   957392
  </price>
  <rating>
   4.79
  </rating>
  <reviews>
   950068
  </reviews>
  <new>
   +
  </new>
  <exclusive>
   yes
  </exclusive>
  <sporty>
   no
  </sporty>
 </clothing>
 <clothing>
  <id>
   273005110
  </id>
  <name>
   Adidas Jacket V-1813
  </name>
  <category>
   Jacket
  </category>
  <size>
   XXL
  </size>
  <color>
   Зеленый
  </color>
  <material>
   Нейлон
  </material>
  <price>
   687963
  </price>
  <rating>
   3.64
  </rating>
  <reviews>
   453447
  </reviews>
  <exclusive>
   yes
  </exclusive>
  <sporty>
   no
  </sporty>
 </clothing>
 <clothing>
  <id>
   233753753
  </id>
  <name>
   New Balance Pants E-9991
  </name>
  <category>
   Pants
  </category>
  <size>
   M
  </size>
  <color>
   Фиолетовый
  </color>
  <material>
   Нейлон
  </material>
  <price>
   294335
  </price>
  <rating>
   3.43
  </rating>
  <reviews>
   326883
  </reviews>
  <new>
   -
  </new>
  <exclusive>
   no
  </exclusive>
  <sporty>
   no
  </sporty>
 </clothing>
 <clothing>
  <id>
   503514742
  </id>
  <name>
   Nike Dress M-4166
  </name>
  <category>
   Dress
  </category>
  <size>
   M
  </size>
  <color>
   Голубой
  </color>
  <material>
   Нейлон
  </material>
  <price>
   424825
  </price>
  <rating>
   3.81
  </rating>
  <reviews>
   79802
  </reviews>
  <new>
   -
  </new>
 </clothing>
 <clothing>
  <id>
   588333036
  </id>
  <name>
   Asics Umbrellas U-6601
  </name>
  <category>
   Umbrellas
  </category>
  <size>
   XXL
  </size>
  <color>
   Красный
  </color>
  <material>
   Полиэстер
  </material>
  <price>
   322245
  </price>
  <rating>
   3.16
  </rating>
  <reviews>
   314447
  </reviews>
  <exclusive>
   yes
  </exclusive>
  <sporty>
   no
  </sporty>
 </clothing>
 <clothing>
  <id>
   291082390
  </id>
  <name>
   PleinSport Sweater T-8218
  </name>
  <category>
   Sweater
  </category>
  <size>
   M
  </size>
  <color>
   Красный
  </color>
  <material>
   Нейлон
  </material>
  <price>
   153682
  </price>
  <rating>
   2.47
  </rating>
  <reviews>
   830137
  </reviews>
  <new>
   -
  </new>
  <exclusive>
   no
  </exclusive>
  <sporty>
   no
  </sporty>
 </clothing>
 <clothing>
  <id>
   580746627
  </id>
  <name>
   DC T-shirt G-9039
  </name>
  <category>
   T-shirt
  </category>
  <size>
   XXL
  </size>
  <color>
   Голубой
  </color>
  <material>
   Кожа
  </material>
  <price>
   300688
  </price>
  <rating>
   4.97
  </rating>
  <reviews>
   413507
  </reviews>
  <new>
   -
  </new>
  <sporty>
   no
  </sporty>
 </clothing>
 <clothing>
  <id>
   470218037
  </id>
  <name>
   DC Pants F-3715
  </name>
  <category>
   Pants
  </category>
  <size>
   XL
  </size>
  <color>
   Фиолетовый
  </color>
  <material>
   Вискоза
  </material>
  <price>
   124209
  </price>
  <rating>
   4.44
  </rating>
  <reviews>
   324263
  </reviews>
 </clothing>
 <clothing>
  <id>
   573626260
  </id>
  <name>
   Fila Sweater F-1475
  </name>
  <category>
   Sweater
  </category>
  <size>
   M
  </size>
  <color>
   Фиолетовый
  </color>
  <material>
   Шелк
  </material>
  <price>
   391803
  </price>
  <rating>
   1.43
  </rating>
  <reviews>
   357208
  </reviews>
 </clothing>
 <clothing>
  <id>
   423191841
  </id>
  <name>
   Asics Dress C-1987
  </name>
  <category>
   Dress
  </category>
  <size>
   L
  </size>
  <color>
   Фиолетовый
  </color>
  <material>
   Лен
  </material>
  <price>
   879313
  </price>
  <rating>
   3.01
  </rating>
  <reviews>
   242747
  </reviews>
  <new>
   -
  </new>
  <sporty>
   no
  </sporty>
 </clothing>
 <clothing>
  <id>
   705283243
  </id>
  <name>
   Converse Pants Y-9984
  </name>
  <category>
   Pants
  </category>
  <size>
   XXL
  </size>
  <color>
   Синий
  </color>
  <material>
   Нейлон
  </material>
  <price>
   482357
  </price>
  <rating>
   4.83
  </rating>
  <reviews>
   788852
  </reviews>
  <new>
   +
  </new>
  <exclusive>
   no
  </exclusive>
  <sporty>
   no
  </sporty>
 </clothing>
 <clothing>
  <id>
   666813167
  </id>
  <name>
   Converse Gloves C-2379
  </name>
  <category>
   Gloves
  </category>
  <size>
   M
  </size>
  <color>
   Желтый
  </color>
  <material>
   Вискоза
  </material>
  <price>
   131523
  </price>
  <rating>
   3.4
  </rating>
  <reviews>
   408314
  </reviews>
  <new>
   -
  </new>
  <exclusive>
   no
  </exclusive>
  <sporty>
   yes
  </sporty>
 </clothing>
 <clothing>
  <id>
   983919312
  </id>
  <name>
   Lacoste Socks T-7636
  </name>
  <category>
   Socks
  </category>
  <size>
   XXL
  </size>
  <color>
   Фиолетовый
  </color>
  <material>
   Хлопок
  </material>
  <price>
   132322
  </price>
  <rating>
   1.14
  </rating>
  <reviews>
   659251
  </reviews>
  <new>
   -
  </new>
  <sporty>
   no
  </sporty>
 </clothing>
 <clothing>
  <id>
   827514308
  </id>
  <name>
   DC Shirt T-8613
  </name>
  <category>
   Shirt
  </category>
  <size>
   M
  </size>
  <color>
   Фиолетовый
  </color>
  <material>
   Нейлон
  </material>
  <price>
   442746
  </price>
  <rating>
   3.04
  </rating>
  <reviews>
   146416
  </reviews>
  <exclusive>
   yes
  </exclusive>
  <sporty>
   no
  </sporty>
 </clothing>
 <clothing>
  <id>
   697831105
  </id>
  <name>
   Vans Jeans S-4765
  </name>
  <category>
   Jeans
  </category>
  <size>
   M
  </size>
  <color>
   Красный
  </color>
  <material>
   Шерсть
  </material>
  <price>
   422511
  </price>
  <rating>
   2.1
  </rating>
  <reviews>
   798653
  </reviews>
  <new>
   +
  </new>
  <exclusive>
   no
  </exclusive>
  <sporty>
   yes
  </sporty>
 </clothing>
</clothing-items>
