<?xml version="1.0" encoding="utf-8"?>
<clothing-items>
 <clothing>
  <id>
   537758903
  </id>
  <name>
   Under Armour Shoes M-5006
  </name>
  <category>
   Shoes
  </category>
  <size>
   XL
  </size>
  <color>
   Зеленый
  </color>
  <material>
   Нейлон
  </material>
  <price>
   104129
  </price>
  <rating>
   1.43
  </rating>
  <reviews>
   949940
  </reviews>
  <new>
   -
  </new>
  <exclusive>
   yes
  </exclusive>
 </clothing>
 <clothing>
  <id>
   868808358
  </id>
  <name>
   Converse Handbags C-6052
  </name>
  <category>
   Handbags
  </category>
  <size>
   XL
  </size>
  <color>
   Зеленый
  </color>
  <material>
   Вискоза
  </material>
  <price>
   346877
  </price>
  <rating>
   4.66
  </rating>
  <reviews>
   687740
  </reviews>
  <new>
   -
  </new>
  <exclusive>
   no
  </exclusive>
  <sporty>
   yes
  </sporty>
 </clothing>
 <clothing>
  <id>
   903897191
  </id>
  <name>
   Adidas Dress B-5023
  </name>
  <category>
   Dress
  </category>
  <size>
   XL
  </size>
  <color>
   Желтый
  </color>
  <material>
   Вискоза
  </material>
  <price>
   779980
  </price>
  <rating>
   1.52
  </rating>
  <reviews>
   922489
  </reviews>
  <new>
   -
  </new>
  <exclusive>
   yes
  </exclusive>
 </clothing>
 <clothing>
  <id>
   280777944
  </id>
  <name>
   Vans Shirt Q-2649
  </name>
  <category>
   Shirt
  </category>
  <size>
   XL
  </size>
  <color>
   Синий
  </color>
  <material>
   Нейлон
  </material>
  <price>
   809544
  </price>
  <rating>
   4.0
  </rating>
  <reviews>
   489294
  </reviews>
  <new>
   -
  </new>
  <sporty>
   no
  </sporty>
 </clothing>
 <clothing>
  <id>
   367009909
  </id>
  <name>
   Fila Jeans D-3800
  </name>
  <category>
   Jeans
  </category>
  <size>
   S
  </size>
  <color>
   Красный
  </color>
  <material>
   Лен
  </material>
  <price>
   590401
  </price>
  <rating>
   3.4
  </rating>
  <reviews>
   623049
  </reviews>
  <sporty>
   no
  </sporty>
 </clothing>
 <clothing>
  <id>
   469828936
  </id>
  <name>
   Asics Pants H-8753
  </name>
  <category>
   Pants
  </category>
  <size>
   L
  </size>
  <color>
   Голубой
  </color>
  <material>
   Кожа
  </material>
  <price>
   559984
  </price>
  <rating>
   3.06
  </rating>
  <reviews>
   175465
  </reviews>
  <new>
   -
  </new>
  <sporty>
   yes
  </sporty>
 </clothing>
 <clothing>
  <id>
   880285330
  </id>
  <name>
   Nike Umbrellas K-9616
  </name>
  <category>
   Umbrellas
  </category>
  <size>
   XXL
  </size>
  <color>
   Фиолетовый
  </color>
  <material>
   Полиэстер
  </material>
  <price>
   360789
  </price>
  <rating>
   3.4
  </rating>
  <reviews>
   281880
  </reviews>
  <exclusive>
   no
  </exclusive>
 </clothing>
 <clothing>
  <id>
   664066840
  </id>
  <name>
   DC Shirt U-6016
  </name>
  <category>
   Shirt
  </category>
  <size>
   XL
  </size>
  <color>
   Фиолетовый
  </color>
  <material>
   Лен
  </material>
  <price>
   921848
  </price>
  <rating>
   4.38
  </rating>
  <reviews>
   640326
  </reviews>
  <new>
   -
  </new>
  <exclusive>
   no
  </exclusive>
  <sporty>
   no
  </sporty>
 </clothing>
 <clothing>
  <id>
   295606391
  </id>
  <name>
   Fila Hat W-7113
  </name>
  <category>
   Hat
  </category>
  <size>
   XL
  </size>
  <color>
   Красный
  </color>
  <material>
   Хлопок
  </material>
  <price>
   284510
  </price>
  <rating>
   3.65
  </rating>
  <reviews>
   711351
  </reviews>
  <new>
   +
  </new>
  <exclusive>
   no
  </exclusive>
  <sporty>
   yes
  </sporty>
 </clothing>
 <clothing>
  <id>
   537444440
  </id>
  <name>
   Vans Jacket Q-3185
  </name>
  <category>
   Jacket
  </category>
  <size>
   L
  </size>
  <color>
   Желтый
  </color>
  <material>
   Лен
  </material>
  <price>
   606439
  </price>
  <rating>
   4.06
  </rating>
  <reviews>
   618622
  </reviews>
  <exclusive>
   no
  </exclusive>
  <sporty>
   yes
  </sporty>
 </clothing>
 <clothing>
  <id>
   598719631
  </id>
  <name>
   Brooks Handbags C-3468
  </name>
  <category>
   Handbags
  </category>
  <size>
   S
  </size>
  <color>
   Голубой
  </color>
  <material>
   Шелк
  </material>
  <price>
   391122
  </price>
  <rating>
   1.95
  </rating>
  <reviews>
   504258
  </reviews>
  <new>
   -
  </new>
  <sporty>
   no
  </sporty>
 </clothing>
 <clothing>
  <id>
   568758673
  </id>
  <name>
   Adidas Dress I-8355
  </name>
  <category>
   Dress
  </category>
  <size>
   M
  </size>
  <color>
   Фиолетовый
  </color>
  <material>
   Шелк
  </material>
  <price>
   658756
  </price>
  <rating>
   2.76
  </rating>
  <reviews>
   472206
  </reviews>
  <exclusive>
   no
  </exclusive>
  <sporty>
   no
  </sporty>
 </clothing>
 <clothing>
  <id>
   521882081
  </id>
  <name>
   Under Armour T-shirt X-7715
  </name>
  <category>
   T-shirt
  </category>
  <size>
   L
  </size>
  <color>
   Желтый
  </color>
  <material>
   Лен
  </material>
  <price>
   370364
  </price>
  <rating>
   2.42
  </rating>
  <reviews>
   23812
  </reviews>
  <sporty>
   no
  </sporty>
 </clothing>
 <clothing>
  <id>
   191637883
  </id>
  <name>
   Brooks Hat B-5571
  </name>
  <category>
   Hat
  </category>
  <size>
   M
  </size>
  <color>
   Красный
  </color>
  <material>
   Полиэстер
  </material>
  <price>
   383557
  </price>
  <rating>
   1.49
  </rating>
  <reviews>
   956558
  </reviews>
 </clothing>
 <clothing>
  <id>
   963610989
  </id>
  <name>
   Converse Hat B-3843
  </name>
  <category>
   Hat
  </category>
  <size>
   M
  </size>
  <color>
   Фиолетовый
  </color>
  <material>
   Кожа
  </material>
  <price>
   818768
  </price>
  <rating>
   2.0
  </rating>
  <reviews>
   53973
  </reviews>
  <new>
   -
  </new>
  <exclusive>
   no
  </exclusive>
 </clothing>
 <clothing>
  <id>
   505016725
  </id>
  <name>
   Adidas Socks L-8629
  </name>
  <category>
   Socks
  </category>
  <size>
   XL
  </size>
  <color>
   Зеленый
  </color>
  <material>
   Нейлон
  </material>
  <price>
   795941
  </price>
  <rating>
   2.74
  </rating>
  <reviews>
   461254
  </reviews>
  <new>
   -
  </new>
  <sporty>
   yes
  </sporty>
 </clothing>
 <clothing>
  <id>
   424481080
  </id>
  <name>
   Converse Umbrellas Q-3121
  </name>
  <category>
   Umbrellas
  </category>
  <size>
   XXL
  </size>
  <color>
   Фиолетовый
  </color>
  <material>
   Шерсть
  </material>
  <price>
   773054
  </price>
  <rating>
   3.28
  </rating>
  <reviews>
   910076
  </reviews>
  <new>
   +
  </new>
  <exclusive>
   yes
  </exclusive>
 </clothing>
 <clothing>
  <id>
   519293576
  </id>
  <name>
   Asics Sweater G-1642
  </name>
  <category>
   Sweater
  </category>
  <size>
   XXL
  </size>
  <color>
   Красный
  </color>
  <material>
   Шелк
  </material>
  <price>
   111933
  </price>
  <rating>
   4.2
  </rating>
  <reviews>
   438330
  </reviews>
  <new>
   -
  </new>
  <exclusive>
   yes
  </exclusive>
 </clothing>
 <clothing>
  <id>
   309280675
  </id>
  <name>
   Adidas T-shirt J-6899
  </name>
  <category>
   T-shirt
  </category>
  <size>
   M
  </size>
  <color>
   Желтый
  </color>
  <material>
   Хлопок
  </material>
  <price>
   678618
  </price>
  <rating>
   4.36
  </rating>
  <reviews>
   604851
  </reviews>
  <exclusive>
   no
  </exclusive>
  <sporty>
   yes
  </sporty>
 </clothing>
 <clothing>
  <id>
   407260314
  </id>
  <name>
   Under Armour Dress Y-1946
  </name>
  <category>
   Dress
  </category>
  <size>
   M
  </size>
  <color>
   Зеленый
  </color>
  <material>
   Вискоза
  </material>
  <price>
   223412
  </price>
  <rating>
   4.24
  </rating>
  <reviews>
   982240
  </reviews>
  <new>
   -
  </new>
  <exclusive>
   no
  </exclusive>
  <sporty>
   no
  </sporty>
 </clothing>
 <clothing>
  <id>
   498557024
  </id>
  <name>
   Brooks Sweater I-2786
  </name>
  <category>
   Sweater
  </category>
  <size>
   L
  </size>
  <color>
   Голубой
  </color>
  <material>
   Полиэстер
  </material>
  <price>
   893422
  </price>
  <rating>
   4.13
  </rating>
  <reviews>
   989468
  </reviews>
  <new>
   +
  </new>
 </clothing>
 <clothing>
  <id>
   452665300
  </id>
  <name>
   Addidas Jacket K-2326
  </name>
  <category>
   Jacket
  </category>
  <size>
   L
  </size>
  <color>
   Зеленый
  </color>
  <material>
   Вискоза
  </material>
  <price>
   953153
  </price>
  <rating>
   1.66
  </rating>
  <reviews>
   705230
  </reviews>
  <new>
   -
  </new>
  <exclusive>
   no
  </exclusive>
 </clothing>
 <clothing>
  <id>
   232991602
  </id>
  <name>
   Brooks Jacket P-7240
  </name>
  <category>
   Jacket
  </category>
  <size>
   S
  </size>
  <color>
   Оранжевый
  </color>
  <material>
   Полиэстер
  </material>
  <price>
   385272
  </price>
  <rating>
   2.13
  </rating>
  <reviews>
   293256
  </reviews>
  <new>
   +
  </new>
  <exclusive>
   no
  </exclusive>
 </clothing>
 <clothing>
  <id>
   164441144
  </id>
  <name>
   Fila Shirt G-7824
  </name>
  <category>
   Shirt
  </category>
  <size>
   S
  </size>
  <color>
   Зеленый
  </color>
  <material>
   Хлопок
  </material>
  <price>
   654059
  </price>
  <rating>
   4.31
  </rating>
  <reviews>
   252387
  </reviews>
  <exclusive>
   no
  </exclusive>
  <sporty>
   no
  </sporty>
 </clothing>
 <clothing>
  <id>
   899886205
  </id>
  <name>
   Puma T-shirt R-1167
  </name>
  <category>
   T-shirt
  </category>
  <size>
   M
  </size>
  <color>
   Оранжевый
  </color>
  <material>
   Нейлон
  </material>
  <price>
   525318
  </price>
  <rating>
   2.09
  </rating>
  <reviews>
   1467
  </reviews>
 </clothing>
 <clothing>
  <id>
   161568222
  </id>
  <name>
   DC Gloves Z-5400
  </name>
  <category>
   Gloves
  </category>
  <size>
   M
  </size>
  <color>
   Голубой
  </color>
  <material>
   Шерсть
  </material>
  <price>
   117375
  </price>
  <rating>
   2.79
  </rating>
  <reviews>
   261997
  </reviews>
  <new>
   -
  </new>
  <exclusive>
   no
  </exclusive>
 </clothing>
 <clothing>
  <id>
   108563399
  </id>
  <name>
   Adidas Jeans L-1000
  </name>
  <category>
   Jeans
  </category>
  <size>
   S
  </size>
  <color>
   Желтый
  </color>
  <material>
   Вискоза
  </material>
  <price>
   906046
  </price>
  <rating>
   4.89
  </rating>
  <reviews>
   566759
  </reviews>
  <new>
   -
  </new>
 </clothing>
 <clothing>
  <id>
   126009255
  </id>
  <name>
   Lacoste Umbrellas J-9375
  </name>
  <category>
   Umbrellas
  </category>
  <size>
   M
  </size>
  <color>
   Синий
  </color>
  <material>
   Полиэстер
  </material>
  <price>
   760258
  </price>
  <rating>
   2.5
  </rating>
  <reviews>
   981040
  </reviews>
  <exclusive>
   no
  </exclusive>
  <sporty>
   no
  </sporty>
 </clothing>
 <clothing>
  <id>
   234283519
  </id>
  <name>
   Under Armour Umbrellas G-1144
  </name>
  <category>
   Umbrellas
  </category>
  <size>
   XL
  </size>
  <color>
   Голубой
  </color>
  <material>
   Кожа
  </material>
  <price>
   966932
  </price>
  <rating>
   2.81
  </rating>
  <reviews>
   197383
  </reviews>
  <exclusive>
   yes
  </exclusive>
  <sporty>
   no
  </sporty>
 </clothing>
 <clothing>
  <id>
   821784914
  </id>
  <name>
   Reebok Belts A-8420
  </name>
  <category>
   Belts
  </category>
  <size>
   S
  </size>
  <color>
   Зеленый
  </color>
  <material>
   Лен
  </material>
  <price>
   199953
  </price>
  <rating>
   2.05
  </rating>
  <reviews>
   251702
  </reviews>
  <new>
   -
  </new>
 </clothing>
 <clothing>
  <id>
   771844393
  </id>
  <name>
   Converse Dress Z-3575
  </name>
  <category>
   Dress
  </category>
  <size>
   L
  </size>
  <color>
   Фиолетовый
  </color>
  <material>
   Шерсть
  </material>
  <price>
   292083
  </price>
  <rating>
   4.18
  </rating>
  <reviews>
   263436
  </reviews>
  <new>
   -
  </new>
  <sporty>
   no
  </sporty>
 </clothing>
 <clothing>
  <id>
   750617706
  </id>
  <name>
   Vans Blouse D-6475
  </name>
  <category>
   Blouse
  </category>
  <size>
   S
  </size>
  <color>
   Желтый
  </color>
  <material>
   Кожа
  </material>
  <price>
   778359
  </price>
  <rating>
   3.87
  </rating>
  <reviews>
   121694
  </reviews>
  <new>
   -
  </new>
  <sporty>
   yes
  </sporty>
 </clothing>
 <clothing>
  <id>
   691024098
  </id>
  <name>
   PleinSport Dress P-3593
  </name>
  <category>
   Dress
  </category>
  <size>
   L
  </size>
  <color>
   Оранжевый
  </color>
  <material>
   Кожа
  </material>
  <price>
   272927
  </price>
  <rating>
   4.88
  </rating>
  <reviews>
   975535
  </reviews>
  <exclusive>
   no
  </exclusive>
  <sporty>
   yes
  </sporty>
 </clothing>
 <clothing>
  <id>
   508328099
  </id>
  <name>
   PleinSport Pants L-2776
  </name>
  <category>
   Pants
  </category>
  <size>
   S
  </size>
  <color>
   Красный
  </color>
  <material>
   Шерсть
  </material>
  <price>
   254896
  </price>
  <rating>
   2.4
  </rating>
  <reviews>
   849697
  </reviews>
  <exclusive>
   yes
  </exclusive>
  <sporty>
   yes
  </sporty>
 </clothing>
 <clothing>
  <id>
   721436359
  </id>
  <name>
   Asics Jacket K-3178
  </name>
  <category>
   Jacket
  </category>
  <size>
   L
  </size>
  <color>
   Синий
  </color>
  <material>
   Хлопок
  </material>
  <price>
   734940
  </price>
  <rating>
   3.29
  </rating>
  <reviews>
   906196
  </reviews>
  <new>
   +
  </new>
  <exclusive>
   no
  </exclusive>
 </clothing>
 <clothing>
  <id>
   827489952
  </id>
  <name>
   DC Shoes S-4969
  </name>
  <category>
   Shoes
  </category>
  <size>
   L
  </size>
  <color>
   Красный
  </color>
  <material>
   Вискоза
  </material>
  <price>
   195048
  </price>
  <rating>
   1.46
  </rating>
  <reviews>
   811254
  </reviews>
  <new>
   +
  </new>
  <exclusive>
   yes
  </exclusive>
  <sporty>
   no
  </sporty>
 </clothing>
 <clothing>
  <id>
   793430982
  </id>
  <name>
   Under Armour Jeans X-8602
  </name>
  <category>
   Jeans
  </category>
  <size>
   XL
  </size>
  <color>
   Зеленый
  </color>
  <material>
   Кожа
  </material>
  <price>
   298530
  </price>
  <rating>
   3.12
  </rating>
  <reviews>
   718734
  </reviews>
  <new>
   +
  </new>
  <sporty>
   yes
  </sporty>
 </clothing>
 <clothing>
  <id>
   994473846
  </id>
  <name>
   PleinSport Jeans B-3981
  </name>
  <category>
   Jeans
  </category>
  <size>
   L
  </size>
  <color>
   Красный
  </color>
  <material>
   Шерсть
  </material>
  <price>
   329149
  </price>
  <rating>
   4.83
  </rating>
  <reviews>
   997361
  </reviews>
  <new>
   -
  </new>
  <exclusive>
   no
  </exclusive>
 </clothing>
 <clothing>
  <id>
   942094724
  </id>
  <name>
   Reebok Belts Z-1673
  </name>
  <category>
   Belts
  </category>
  <size>
   XL
  </size>
  <color>
   Зеленый
  </color>
  <material>
   Хлопок
  </material>
  <price>
   176745
  </price>
  <rating>
   1.39
  </rating>
  <reviews>
   698185
  </reviews>
  <exclusive>
   yes
  </exclusive>
 </clothing>
 <clothing>
  <id>
   143885824
  </id>
  <name>
   Lacoste Shirt U-8230
  </name>
  <category>
   Shirt
  </category>
  <size>
   XL
  </size>
  <color>
   Синий
  </color>
  <material>
   Лен
  </material>
  <price>
   821113
  </price>
  <rating>
   1.8
  </rating>
  <reviews>
   638004
  </reviews>
  <sporty>
   yes
  </sporty>
 </clothing>
 <clothing>
  <id>
   191194140
  </id>
  <name>
   Addidas Jacket I-5166
  </name>
  <category>
   Jacket
  </category>
  <size>
   M
  </size>
  <color>
   Фиолетовый
  </color>
  <material>
   Лен
  </material>
  <price>
   983065
  </price>
  <rating>
   2.57
  </rating>
  <reviews>
   365174
  </reviews>
  <new>
   +
  </new>
  <exclusive>
   no
  </exclusive>
  <sporty>
   yes
  </sporty>
 </clothing>
 <clothing>
  <id>
   790203948
  </id>
  <name>
   Under Armour Hat N-5293
  </name>
  <category>
   Hat
  </category>
  <size>
   M
  </size>
  <color>
   Фиолетовый
  </color>
  <material>
   Нейлон
  </material>
  <price>
   821876
  </price>
  <rating>
   2.23
  </rating>
  <reviews>
   141483
  </reviews>
  <new>
   -
  </new>
  <exclusive>
   no
  </exclusive>
 </clothing>
 <clothing>
  <id>
   587591187
  </id>
  <name>
   Fila Dress T-7856
  </name>
  <category>
   Dress
  </category>
  <size>
   XL
  </size>
  <color>
   Синий
  </color>
  <material>
   Полиэстер
  </material>
  <price>
   521761
  </price>
  <rating>
   2.99
  </rating>
  <reviews>
   618298
  </reviews>
  <exclusive>
   yes
  </exclusive>
 </clothing>
 <clothing>
  <id>
   427417474
  </id>
  <name>
   Addidas Socks J-5993
  </name>
  <category>
   Socks
  </category>
  <size>
   L
  </size>
  <color>
   Красный
  </color>
  <material>
   Шерсть
  </material>
  <price>
   299447
  </price>
  <rating>
   3.37
  </rating>
  <reviews>
   727444
  </reviews>
  <new>
   -
  </new>
  <exclusive>
   yes
  </exclusive>
 </clothing>
</clothing-items>
